pysx/__init__.py
pysx-0.0.1.dist-info/LICENSE.md
pysx-0.0.1.dist-info/WHEEL
pysx-0.0.1.dist-info/METADATA
pysx-0.0.1.dist-info/RECORD
