Metadata-Version: 2.1
Name: pysx
Version: 0.0.1
Summary: pysx 
Author-email: DK <tk@terminalkitten.com>
Classifier: License :: OSI Approved :: MIT License
Project-URL: Home, https://github.com/terminalkitten/pysx
